allure_combine/__init__.py
allure_combine/combine.py
allure_combine/sinon-9.2.4.js
allure_combine-1.0.11.dist-info/LICENSE
allure_combine-1.0.11.dist-info/METADATA
allure_combine-1.0.11.dist-info/WHEEL
allure_combine-1.0.11.dist-info/entry_points.txt
allure_combine-1.0.11.dist-info/top_level.txt
allure_combine-1.0.11.dist-info/RECORD
