Metadata-Version: 2.1
Name: allure_combine
Version: 1.0.11
Summary: Generate single HTML file from allure report.
Home-page: https://github.com/MihanEntalpo/allure-single-html-file
Author: MihanEntalpo, Sine.wang
Author-email: mihanentalpo@yandex.ru, sinecelia.wang@gmail.com
Maintainer: Sine.wang
Maintainer-email: sinecelia.wang@gmail.com
License: MIT
Platform: UNKNOWN
Classifier: Development Status :: 4 - Beta
Classifier: Framework :: Pytest
Classifier: Intended Audience :: Developers
Classifier: Topic :: Software Development :: Testing
Classifier: Programming Language :: Python
Classifier: Programming Language :: Python :: 3
Classifier: Programming Language :: Python :: 3.6
Classifier: Programming Language :: Python :: 3.7
Classifier: Programming Language :: Python :: 3.8
Classifier: Programming Language :: Python :: 3 :: Only
Classifier: Programming Language :: Python :: Implementation :: CPython
Classifier: Programming Language :: Python :: Implementation :: PyPy
Classifier: Operating System :: OS Independent
Classifier: License :: OSI Approved :: MIT License
Requires-Python: >=3.6
License-File: LICENSE
